hela_utils/__init__.py
hela_utils/eloqua/__init__.py
hela_utils/eloqua/utils.py
hela_utils/luigi_scheduler/__init__.py
hela_utils/luigi_scheduler/requests_fetcher.py
hela_utils/luigi_scheduler/scheduler.py
hela_utils/luigi_scheduler/scheduler_factory.py
hela_utils/metrics/__init__.py
hela_utils/metrics/metric_monitoring.py
hela_utils/metrics/metrics_pusher.py
hela_utils/test_utils/__init__.py
hela_utils/test_utils/luigi_mock.py
hela_utils/vdm/__init__.py
hela_utils/vdm/helpers.py
hela_utils/vdm/utils.py
hela_utils-0.3.6.dist-info/METADATA
hela_utils-0.3.6.dist-info/WHEEL
hela_utils-0.3.6.dist-info/top_level.txt
hela_utils-0.3.6.dist-info/RECORD
