Metadata-Version: 2.1
Name: hela-utils
Version: 0.3.6
Summary: Some luigi utility classes
Home-page: https://gitlab.corp.redhat.com/mkt-ops-de/hela-utils.git
Author: Edward Brennan
Author-email: ebrennan@redhat.com
Maintainer: Pramod Toraskar
Maintainer-email: ptoraska@redhat.com
License: UNKNOWN
Platform: UNKNOWN
Classifier: Programming Language :: Python :: 3
Classifier: License :: OSI Approved :: MIT License
Classifier: Operating System :: OS Independent
Requires-Dist: requests
